update_route53.py
update_route53-0.0.1.dist-info/LICENSE
update_route53-0.0.1.dist-info/METADATA
update_route53-0.0.1.dist-info/WHEEL
update_route53-0.0.1.dist-info/entry_points.txt
update_route53-0.0.1.dist-info/top_level.txt
update_route53-0.0.1.dist-info/RECORD
