Metadata-Version: 2.1
Name: update-route53
Version: 0.0.1
Summary: Updates route53 for a name and IP address.
Home-page: https://github.com/ccoakley/update-route53
Author: Christopher Coakley
Author-email: update-route53@tekabal.com
License: UNKNOWN
Platform: UNKNOWN
Classifier: Programming Language :: Python :: 3
Classifier: License :: OSI Approved :: MIT License
Classifier: Operating System :: OS Independent
Requires-Dist: boto3 (>=1.9.28)
